odoo/addons/hr_attendance_modification_tracking/README.rst
odoo/addons/hr_attendance_modification_tracking/__init__.py
odoo/addons/hr_attendance_modification_tracking/__manifest__.py
odoo/addons/hr_attendance_modification_tracking/hooks.py
odoo/addons/hr_attendance_modification_tracking/i18n/ca.po
odoo/addons/hr_attendance_modification_tracking/i18n/ca_ES.po
odoo/addons/hr_attendance_modification_tracking/i18n/es.po
odoo/addons/hr_attendance_modification_tracking/i18n/hr_attendance_modification_tracking.pot
odoo/addons/hr_attendance_modification_tracking/i18n/it.po
odoo/addons/hr_attendance_modification_tracking/migrations/13.0.1.1.0/pre-migration.py
odoo/addons/hr_attendance_modification_tracking/models/__init__.py
odoo/addons/hr_attendance_modification_tracking/models/hr_attendance.py
odoo/addons/hr_attendance_modification_tracking/readme/CONTRIBUTORS.rst
odoo/addons/hr_attendance_modification_tracking/readme/DESCRIPTION.rst
odoo/addons/hr_attendance_modification_tracking/static/description/icon.png
odoo/addons/hr_attendance_modification_tracking/static/description/index.html
odoo/addons/hr_attendance_modification_tracking/tests/__init__.py
odoo/addons/hr_attendance_modification_tracking/tests/test_hr_attendance.py
odoo/addons/hr_attendance_modification_tracking/views/hr_attendance_view.xml
odoo13_addon_hr_attendance_modification_tracking-13.0.1.1.1.dev9.dist-info/METADATA
odoo13_addon_hr_attendance_modification_tracking-13.0.1.1.1.dev9.dist-info/WHEEL
odoo13_addon_hr_attendance_modification_tracking-13.0.1.1.1.dev9.dist-info/top_level.txt
odoo13_addon_hr_attendance_modification_tracking-13.0.1.1.1.dev9.dist-info/RECORD
